{
  "vertices": [
    {
      "id": "1",
      "name": "Item",
      "in": [
        14219,
        86193,
        79591
      ],
      "out": []
    },
    {
      "id": "72663",
      "name": "beverage",
      "in": [],
      "out": [
        14219,
        26822
      ]
    },
    {
      "id": "93353",
      "name": "food",
      "in": [],
      "out": [
        86193
      ]
    },
    {
      "id": "9533",
      "name": "alc beverage",
      "in": [
        36323,
        26822
      ],
      "out": [
        79591
      ]
    },
    {
      "id": "63087",
      "name": "beer",
      "in": [],
      "out": [
        36323
      ]
    },
    {
      "id": "67148",
      "name": "brand",
      "in": [],
      "out": []
    },
    {
      "id": "85081",
      "name": "amstel",
      "in": [],
      "out": []
    },
    {
      "id": "41459",
      "name": "skoll",
      "in": [],
      "out": []
    },
    {
      "id": "25466",
      "name": "origin",
      "in": [],
      "out": []
    },
    {
      "id": "9460",
      "name": "italy",
      "in": [],
      "out": []
    },
    {
      "id": "55345",
      "name": "cheese",
      "in": [],
      "out": []
    },
    {
      "id": "wpq",
      "name": "ddd",
      "in": [
        "fth"
      ],
      "out": []
    },
    {
      "id": "igb",
      "name": "ddda",
      "in": [],
      "out": [
        "fth"
      ]
    }
  ]
}